{
  "id": "generation",
  "name": "generation",
  "articles": [
    {
      "id": "building-your-app-creating-executables-nwjs",
      "slug": "building-your-app-creating-executables-nwjs",
      "collection": null,
      "keywords": [
        "node-webkit",
        "desktop",
        "executable",
        "distribution",
        "generation",
        "javascript"
      ],
      "original": {
        "blogLink": "https://www.packtpub.com/books/content/blogs",
        "blogName": "Packt books",
        "url": "https://www.packtpub.com/books/content/building-your-app-creating-executables-nwjs"
      },
      "title": "Building Your App: Creating Executables for NW.js",
      "summary": "NW.js is great for creating desktop applications using Web app technologies. If you're not familiar with NW.js, I'd advise you to read an introductory article like Creating Your First Desktop App With HTML, JS and Node-WebKit to get a good base first. This is a slightly more advanced article intended for anyone interested into distributing their NW.js app to Windows users.\n",
      "published_at": "2015-11-17T00:00:00.000Z",
      "renderedSummary": "<p>NW.js is great for creating desktop applications using Web app technologies. If you're not familiar with NW.js, I'd advise you to read an introductory article like Creating Your First Desktop App With HTML, JS and Node-WebKit to get a good base first. This is a slightly more advanced article intended for anyone interested into distributing their NW.js app to Windows users.</p>\n"
    }
  ]
}